Metadata-Version: 2.1
Name: prsum
Version: 0.0.0
Summary: Quick PR summary.
Home-page: https://https://github.com/tlylt/prsum/tlylt/prsum
Author: Liu Yongliang
Author-email: liu_yongliang@hotmail.com
License: MIT
Project-URL: Changelog, https://https://github.com/tlylt/prsum/tlylt/prsum/blob/master/CHANGELOG.rst
Project-URL: Issue Tracker, https://https://github.com/tlylt/prsum/tlylt/prsum/issues
Classifier: Development Status :: 5 - Production/Stable
Classifier: Intended Audience :: Developers
Classifier: License :: OSI Approved :: MIT License
Classifier: Operating System :: Unix
Classifier: Operating System :: POSIX
Classifier: Operating System :: Microsoft :: Windows
Classifier: Programming Language :: Python
Classifier: Programming Language :: Python :: 3
Classifier: Programming Language :: Python :: 3 :: Only
Classifier: Programming Language :: Python :: 3.7
Classifier: Programming Language :: Python :: 3.8
Classifier: Programming Language :: Python :: 3.9
Classifier: Programming Language :: Python :: 3.10
Classifier: Programming Language :: Python :: 3.11
Classifier: Programming Language :: Python :: Implementation :: CPython
Classifier: Programming Language :: Python :: Implementation :: PyPy
Classifier: Topic :: Utilities
Requires-Python: >=3.7
License-File: LICENSE
